ai/__init__.py
ai/cdas.py
ai.cdas-1.2.3.dist-info/METADATA
ai.cdas-1.2.3.dist-info/WHEEL
ai.cdas-1.2.3.dist-info/top_level.txt
ai.cdas-1.2.3.dist-info/RECORD
