Metadata-Version: 2.1
Name: ai.cdas
Version: 1.2.3
Summary: Python interface to CDAS data via REST API
Home-page: https://bitbucket.org/isavnin/ai.cdas
Author: Alexey Isavnin
Author-email: alexey.isavnin@gmail.com
License: MIT
Keywords: coordinated data analysis web cdaweb cdas spdf research space physics data facility nasa science
Platform: UNKNOWN
Classifier: Development Status :: 5 - Production/Stable
Classifier: Environment :: Console
Classifier: Intended Audience :: Science/Research
Classifier: License :: OSI Approved :: MIT License
Classifier: Programming Language :: Python :: 3
Provides-Extra: CDF
